{
  "Barre de l'Ender": "end_rod",
  "Porte en chêne pâle": "pale_oak_door",
  "Pousse de chêne pâle": "pale_oak_sapling",
  "Feuilles de chêne pâle": "pale_oak_leaves",
  "Capteur Sculk": "sculk_sensor",
  "Sculk": "sculk",
  "Veine de sculk": "sculk_vein",
  "Catalyseur de sculk": "sculk_catalyst",
  "Hurleur Sculk": "sculk_shrieker",
  "Profondoise renforcée": "reinforced_deepslate",
  "Œufs de grenouille": "frog_spawn",
  "Grenoumière nacrée": "pearlescent_froglight",
  "Grenoumière verdoyante": "verdant_froglight",
  "Grenoumière ocrée": "ochre_froglight",
  "Bouette": "mud",
  "Terre crue": "packed_mud",
  "Briques crues": "mud_bricks",
  "Dalle de briques crues": "mud_brick_slab",
  "Dalle double de briques crues": "mud_brick_double_slab",
  "Escaliers de briques crues": "mud_brick_stairs",
  "Mur en briques crues": "mud_brick_wall",
  "Feuilles de palétuvier": "mangrove_leaves",
  "Propagule de palétuvier": "mangrove_propagule",
  "Racines de palétuvier": "mangrove_roots",
  "Racines de palétuvier bouetteuses": "muddy_mangrove_roots",
  "Bûche de palétuvier": "mangrove_log",
  "Bûche de palétuvier écorcée": "stripped_mangrove_log",
  "Planches de palétuvier": "mangrove_planks",
  "Bouton en palétuvier": "mangrove_button",
  "Escaliers en palétuvier": "mangrove_stairs",
  "Dalle en palétuvier": "mangrove_slab",
  "Dalle double en palétuvier": "mangrove_double_slab",
  "Plaque de pression en palétuvier": "mangrove_pressure_plate",
  "Clôture en palétuvier": "mangrove_fence",
  "Porte de clôture en palétuvier": "mangrove_fence_gate",
  "Pancarte en palétuvier": "mangrove_standing_sign",
  "Pancarte murale en palétuvier": "mangrove_wall_sign",
  "Pancarte suspendue en palétuvier": "mangrove_hanging_sign",
  "Porte en palétuvier": "mangrove_door",
  "Trappe en palétuvier": "mangrove_trapdoor",
  "Bois de palétuvier": "mangrove_wood",
  "Bois de palétuvier écorcé": "stripped_mangrove_wood",
  "Bloc de bambou": "bamboo_block",
  "Bouton en bambou": "bamboo_button",
  "Porte en bambou": "bamboo_door",
  "Porte de clôture en bambou": "bamboo_fence_gate",
  "Clôture en bambou": "bamboo_fence",
  "Dalle de mosaïque de bambou": "bamboo_mosaic_slab",
  "Dalle double en bambou mosaïque": "bamboo_mosaic_double_slab",
  "Escaliers de mosaïque de bambou": "bamboo_mosaic_stairs",
  "Mosaïque de bambou": "bamboo_mosaic",
  "Planches de bambou": "bamboo_planks",
  "Plaque de pression en bambou": "bamboo_pressure_plate",
  "Pousse d'arbre de bambou": "bamboo_sapling",
  "Pancarte en bambou": "bamboo_standing_sign",
  "Panneau mural en bambou": "bamboo_wall_sign",
  "Pancarte suspendue en bambou": "bamboo_hanging_sign",
  "Dalle en bambou": "bamboo_slab",
  "Dalle double en bambou": "bamboo_double_slab",
  "Escaliers en bambou": "bamboo_stairs",
  "Trappe en bambou": "bamboo_trapdoor",
  "Capteur Sculk calibré": "calibrated_sculk_sensor",
  "Bouton en cerisier": "cherry_button",
  "Dalle double en cerisier": "cherry_double_slab",
  "Porte de clôture en cerisier": "cherry_fence_gate",
  "Clôture en cerisier": "cherry_fence",
  "Feuilles de cerisier": "cherry_leaves",
  "Bûche de cerisier": "cherry_log",
  "Planches de cerisier": "cherry_planks",
  "Plaque de pression en cerisier": "cherry_pressure_plate",
  "Pousse de cerisier": "cherry_sapling",
  "Pancarte en cerisier": "cherry_standing_sign",
  "Panneau mural en cerisier": "cherry_wall_sign",
  "Pancarte suspendue en cerisier": "cherry_hanging_sign",
  "Dalle en cerisier": "cherry_slab",
  "Escaliers en cerisier": "cherry_stairs",
  "Porte en cerisier": "cherry_door",
  "Trappe en cerisier": "cherry_trapdoor",
  "Bois de cerisier": "cherry_wood",
  "Bibliothèque sculptée": "chiseled_bookshelf",
  "Tuf ciselé": "chiseled_tuff",
  "Briques de tuf ciselées": "chiseled_tuff_bricks",
  "Pot décoré": "decorated_pot",
  "Pétales roses": "pink_petals",
  "Bloc de bambou écorcé": "stripped_bamboo_block",
  "Bûche de cerisier écorcée": "stripped_cherry_log",
  "Bois de cerisier écorcé": "stripped_cherry_wood",
  "Gravelle suspecte": "suspicious_gravel",
  "Sable suspect": "suspicious_sand",
  "Clôture en acacia": "acacia_fence",
  "Porte de clôture en acacia": "acacia_fence_gate",
  "Rails déclencheurs": "activator_rail",
  "Autoriser": "allow",
  "Air": "air",
  "Refuser": "deny",
  "Bordure": "border_block",
  "Enclume": "anvil",
  "Enclume ébréchée": "chipped_anvil",
  "Enclume endommagée": "damaged_anvil",
  "Barrière invisible": "barrier",
  "Balise": "beacon",
  "Ruche": "beehive",
  "Nid d'abeilles": "bee_nest",
  "Cible": "target",
  "Lit": "bed",
  "Bedrock": "bedrock",
  "Cloche": "bell",
  "Conduit": "conduit",
  "Betterave": "beetroot",
  "Grosse platefeuille": "big_dripleaf",
  "Petites platefeuilles": "small_dripleaf_block",
  "Racines suspendues": "hanging_roots",
  "Terre avec racines": "dirt_with_roots",
  "Fleur sporifère": "spore_blossom",
  "Feuilles d'azalée": "azalea_leaves",
  "Feuilles d'azalée en fleurs": "azalea_leaves_flowered",
  "Azalée": "azalea",
  "Azalée en fleurs": "flowering_azalea",
  "Lianes des cavernes": "cave_vines",
  "Bloc de mousse": "moss_block",
  "Tapis de mousse": "moss_carpet",
  "Porte en bouleau": "birch_door",
  "Clôture en bouleau": "birch_fence",
  "Porte de clôture en bouleau": "birch_fence_gate",
  "Haut fourneau": "blast_furnace",
  "Haut fourneau allumé": "lit_blast_furnace",
  "Bloc d'os": "bone_block",
  "Bloc de charbon": "coal_block",
  "Bloc de diamant": "diamond_block",
  "Bloc d'émeraude": "emerald_block",
  "Bloc d'or": "gold_block",
  "Bloc de fer": "iron_block",
  "Bloc de lapis-lazuli": "lapis_block",
  "Bloc de redstone": "redstone_block",
  "Bibliothèque": "bookshelf",
  "Briques": "brick_block",
  "Champignon brun": "brown_mushroom",
  "Tige de champignon": "mushroom_stem",
  "Bloc de champignon brun": "brown_mushroom_block",
  "Bouton en chêne": "wooden_button",
  "Bouton en acacia": "acacia_button",
  "Bouton en bouleau": "birch_button",
  "Bouton en chêne noir": "dark_oak_button",
  "Bouton en acajou": "jungle_button",
  "Bouton en épinette": "spruce_button",
  "Bouton de pierre": "stone_button",
  "Cactus": "cactus",
  "Gâteau": "cake",
  "Varech": "kelp",
  "Bloc de varech séché": "dried_kelp_block",
  "Carottes": "carrots",
  "Citrouille sculptée": "carved_pumpkin",
  "Chaudron": "cauldron",
  "Coffre": "chest",
  "Coffre de l'Ender": "ender_chest",
  "Bloc casse-tête": "jigsaw",
  "Noyau lourd": "heavy_core",
  "Bloc de miel": "honey_block",
  "Bloc de rayon de miel": "honeycomb_block",
  "Magnétite": "lodestone",
  "Germes du Nether": "nether_sprouts",
  "Tige cramoisie": "crimson_stem",
  "Tige tordue": "warped_stem",
  "Tige cramoisie écorcée": "stripped_crimson_stem",
  "Tige tordue écorcée": "stripped_warped_stem",
  "Hyphes cramoisies": "crimson_hyphae",
  "Hyphes tordues": "warped_hyphae",
  "Hyphes cramoisies écorcées": "stripped_crimson_hyphae",
  "Hyphes tordues écorcées": "stripped_warped_hyphae",
  "Planches cramoisies": "crimson_planks",
  "Planches tordues": "warped_planks",
  "Porte cramoisie": "crimson_door",
  "Porte tordue": "warped_door",
  "Trappe cramoisie": "crimson_trapdoor",
  "Trappe tordue": "warped_trapdoor",
  "Pancarte cramoisie": "crimson_wall_sign",
  "Pancarte tordue": "warped_wall_sign",
  "Pancarte suspendue tordue": "warped_hanging_sign",
  "Escaliers cramoisis": "crimson_stairs",
  "Escaliers tordus": "warped_stairs",
  "Clôture cramoisie": "crimson_fence",
  "Clôture tordue": "warped_fence",
  "Porte de clôture cramoisie": "crimson_fence_gate",
  "Porte de clôture tordue": "warped_fence_gate",
  "Bouton cramoisi": "crimson_button",
  "Bouton tordu": "warped_button",
  "Plaque de pression cramoisie": "crimson_pressure_plate",
  "Plaque de pression tordue": "warped_pressure_plate",
  "Dalle cramoisie": "crimson_slab",
  "Dalle tordue": "warped_slab",
  "Lampignon": "shroomlight",
  "Nylium cramoisi": "crimson_nylium",
  "Nylium tordu": "warped_nylium",
  "Basalte": "basalt",
  "Basalte poli": "polished_basalt",
  "Roche noire": "blackstone",
  "Briques de roche noire polie": "polished_blackstone_bricks",
  "Briques en roche noire polie craquelée": "cracked_polished_blackstone_bricks",
  "Escaliers en briques de roche noire polie": "polished_blackstone_brick_stairs",
  "Escaliers en roche noire": "blackstone_stairs",
  "Muret de roche noire": "blackstone_wall",
  "Mur en briques de roche noire polie": "polished_blackstone_brick_wall",
  "Brique de roche noire ciselée": "chiseled_polished_blackstone",
  "Roche noire dorée": "gilded_blackstone",
  "Dalle de roche noire": "blackstone_slab",
  "Dalle double en roche noire": "blackstone_double_slab",
  "Dalle en briques de roche noire polie": "polished_blackstone_brick_slab",
  "Dalle double en briques de roche noire polie": "polished_blackstone_brick_double_slab",
  "Terre des âmes": "soul_soil",
  "Feu des âmes": "soul_fire",
  "Roche noire polie": "polished_blackstone",
  "Escaliers de roche noire polie": "polished_blackstone_stairs",
  "Dalle de roche noire polie": "polished_blackstone_slab",
  "Dalle double de roche noire polie": "polished_blackstone_double_slab",
  "Plaque de pression en roche noire polie": "polished_blackstone_pressure_plate",
  "Bouton de roche noire polie": "polished_blackstone_button",
  "Mur de roche noire polie": "polished_blackstone_wall",
  "Tuf poli": "polished_tuff",
  "Dalle de tuf poli": "polished_tuff_slab",
  "Dalle double en tuf poli": "polished_tuff_double_slab",
  "Escaliers de tuf poli": "polished_tuff_stairs",
  "Mur en tuf poli": "polished_tuff_wall",
  "Feu de camp des âmes": "soul_campfire",
  "Briques du Nether ciselées": "chiseled_nether_bricks",
  "Briques du Nether craquelées": "cracked_nether_bricks",
  "Briques de quartz": "quartz_bricks",
  "Coffre piégé": "trapped_chest",
  "Boîte de Shulker blanche": "white_shulker_box",
  "Boîte de Shulker orange": "orange_shulker_box",
  "Boîte de Shulker magenta": "magenta_shulker_box",
  "Boîte de Shulker bleu pâle": "light_blue_shulker_box",
  "Boîte de Shulker jaune": "yellow_shulker_box",
  "Boîte de Shulker vert lime": "lime_shulker_box",
  "Boîte de Shulker rose": "pink_shulker_box",
  "Boîte de Shulker grise": "gray_shulker_box",
  "Boîte de Shulker gris pâle": "light_gray_shulker_box",
  "Boîte de Shulker cyan": "cyan_shulker_box",
  "Boîte de Shulker mauve": "purple_shulker_box",
  "Boîte de Shulker bleue": "blue_shulker_box",
  "Boîte de Shulker brune": "brown_shulker_box",
  "Boîte de Shulker verte": "green_shulker_box",
  "Boîte de Shulker rouge": "red_shulker_box",
  "Boîte de Shulker noire": "black_shulker_box",
  "Boîte de Shulker": "undyed_shulker_box",
  "Fleur de chorus": "chorus_flower",
  "Plante de chorus": "chorus_plant",
  "Verre blanc": "white_stained_glass",
  "Verre gris pâle": "light_gray_stained_glass",
  "Verre gris": "gray_stained_glass",
  "Verre noir": "black_stained_glass",
  "Verre brun": "brown_stained_glass",
  "Verre rouge": "red_stained_glass",
  "Verre orange": "orange_stained_glass",
  "Verre jaune": "yellow_stained_glass",
  "Verre vert lime": "lime_stained_glass",
  "Verre vert": "green_stained_glass",
  "Verre cyan": "cyan_stained_glass",
  "Verre bleu pâle": "light_blue_stained_glass",
  "Verre bleu": "blue_stained_glass",
  "Verre mauve": "purple_stained_glass",
  "Verre magenta": "magenta_stained_glass",
  "Verre rose": "pink_stained_glass",
  "Vitre blanche": "white_stained_glass_pane",
  "Vitre gris pâle": "light_gray_stained_glass_pane",
  "Vitre grise": "gray_stained_glass_pane",
  "Vitre noire": "black_stained_glass_pane",
  "Vitre brune": "brown_stained_glass_pane",
  "Vitre rouge": "red_stained_glass_pane",
  "Vitre orange": "orange_stained_glass_pane",
  "Vitre jaune": "yellow_stained_glass_pane",
  "Vitre vert lime": "lime_stained_glass_pane",
  "Vitre verte": "green_stained_glass_pane",
  "Vitre cyan": "cyan_stained_glass_pane",
  "Vitre bleu pâle": "light_blue_stained_glass_pane",
  "Vitre bleue": "blue_stained_glass_pane",
  "Vitre mauve": "purple_stained_glass_pane",
  "Vitre magenta": "magenta_stained_glass_pane",
  "Vitre rose": "pink_stained_glass_pane",
  "Glaise": "clay",
  "Terre cuite": "hardened_clay",
  "Terre cuite noire": "black_terracotta",
  "Terre cuite bleue": "blue_terracotta",
  "Terre cuite brune": "brown_terracotta",
  "Terre cuite cyan": "cyan_terracotta",
  "Terre cuite grise": "gray_terracotta",
  "Terre cuite verte": "green_terracotta",
  "Terre cuite bleu pâle": "light_blue_terracotta",
  "Terre cuite vert lime": "lime_terracotta",
  "Terre cuite magenta": "magenta_terracotta",
  "Terre cuite orange": "orange_terracotta",
  "Terre cuite rose": "pink_terracotta",
  "Terre cuite mauve": "purple_terracotta",
  "Terre cuite rouge": "red_terracotta",
  "Terre cuite gris pâle": "light_gray_terracotta",
  "Terre cuite blanche": "white_terracotta",
  "Terre cuite jaune": "yellow_terracotta",
  "Bloc de structure": "structure_block",
  "Structure nulle": "structure_void",
  "Générateur des épreuves": "trial_spawner",
  "Coffre-fort": "vault",
  "Laine noire": "black_wool",
  "Laine bleue": "blue_wool",
  "Laine brune": "brown_wool",
  "Laine cyan": "cyan_wool",
  "Laine grise": "gray_wool",
  "Laine verte": "green_wool",
  "Laine bleu pâle": "light_blue_wool",
  "Laine vert lime": "lime_wool",
  "Laine magenta": "magenta_wool",
  "Laine orange": "orange_wool",
  "Laine rose": "pink_wool",
  "Laine mauve": "purple_wool",
  "Laine rouge": "red_wool",
  "Laine gris pâle": "light_gray_wool",
  "Laine blanche": "white_wool",
  "Laine jaune": "yellow_wool",
  "Mur en fragments de pierres moussus": "mossy_cobblestone_wall",
  "Mur en fragments de pierres": "cobblestone_wall",
  "Muret en granite": "granite_wall",
  "Mur en diorite": "diorite_wall",
  "Mur en andésite": "andesite_wall",
  "Mure en grès": "sandstone_wall",
  "Mur en briques": "brick_wall",
  "Mur en briques de pierre": "stone_brick_wall",
  "Mur en briques de pierre moussue": "mossy_stone_brick_wall",
  "Mur en briques du Nether": "nether_brick_wall",
  "Mur en briques de pierre de l'Ender": "end_stone_brick_wall",
  "Mur en prismarine": "prismarine_wall",
  "Mur en grès rouge": "red_sandstone_wall",
  "Mur de briques rouges du Nether": "red_nether_brick_wall",
  "Cabosse": "cocoa",
  "Bloc de commande": "command_block",
  "Composteur": "composter",
  "Lumière": "light_block_15",
  "Bloc de commande à répétition": "repeating_command_block",
  "Bloc de commande en chaîne": "chain_command_block",
  "Cultures": "wheat",
  "Clôture en chêne noir": "dark_oak_fence",
  "Porte de clôture en chêne noir": "dark_oak_fence_gate",
  "Détecteur solaire": "daylight_detector",
  "Détecteur solaire inversé": "daylight_detector_inverted",
  "Buisson mort": "deadbush",
  "Rails détecteurs": "detector_rail",
  "Terre stérile": "coarse_dirt",
  "Terre": "dirt",
  "Podzol": "podzol",
  "Bloc de purpur": "purpur_block",
  "Pilier de purpur": "purpur_pillar",
  "Pierre pourpre ciselée": "purpur_block",
  "Distributeur": "dispenser",
  "Porte en fer": "iron_door",
  "Porte en bois": "wooden_door",
  "Porte en acacia": "acacia_door",
  "Porte en chêne noir": "dark_oak_door",
  "Porte en acajou": "jungle_door",
  "Porte en épinette": "spruce_door",
  "Grande fougère": "large_fern",
  "Herbe haute": "tall_grass",
  "Pivoines": "peony",
  "Rosier": "rose_bush",
  "Tournesol": "sunflower",
  "Lilas": "lilac",
  "Œuf de Dragon": "dragon_egg",
  "Droppeur": "dropper",
  "Table d'enchantement": "enchanting_table",
  "Cadre de portail de l'Ender": "end_portal_frame",
  "Portail de l'Ender": "end_portal",
  "Terre labourée": "farmland",
  "Table d'archerie": "fletching_table",
  "Clôture en chêne": "oak_fence",
  "Porte de clôture en chêne": "fence_gate",
  "Barreaux de fer": "iron_bars",
  "Feu": "fire",
  "Pissenlit": "dandelion",
  "Racines cramoisies": "crimson_roots",
  "Racines tordues": "warped_roots",
  "Allium": "allium",
  "Orchidées bleues": "blue_orchid",
  "Centaurée bleuet": "cornflower",
  "Houstonies bleues": "azure_bluet",
  "Muguet": "lily_of_the_valley",
  "Marguerite": "oxeye_daisy",
  "Coquelicot": "poppy",
  "Tulipe orange": "orange_tulip",
  "Tulipe rose": "pink_tulip",
  "Tulipe rouge": "red_tulip",
  "Tulipe blanche": "white_tulip",
  "Culture de torche-fleur": "torchflower_crop",
  "Rose de Wither": "wither_rose",
  "Pot de fleurs": "flower_pot",
  "Fourneau": "furnace",
  "Fourneau allumé": "lit_furnace",
  "Verre": "glass",
  "Rails propulseurs": "golden_rail",
  "Gazon": "grass_block",
  "Chemin de terre": "grass_path",
  "Gravelle": "gravel",
  "Botte de paille": "hay_block",
  "Roche du Nether": "netherrack",
  "Sable des âmes": "soul_sand",
  "Entonnoir": "hopper",
  "Glace": "ice",
  "Glace compactée": "packed_ice",
  "Glace bleue": "blue_ice",
  "Glace givrée": "frosted_ice",
  "Trappe en fer": "iron_trapdoor",
  "Jukebox": "jukebox",
  "Clôture en acajou": "jungle_fence",
  "Porte de clôture en acajou": "jungle_fence_gate",
  "Échelle": "ladder",
  "Cadre": "frame",
  "Lave": "lava",
  "Feuilles d'acacia": "acacia_leaves",
  "Feuilles de chêne noir": "dark_oak_leaves",
  "Feuilles de bouleau": "birch_leaves",
  "Feuilles d'acajou": "jungle_leaves",
  "Feuilles de chêne": "oak_leaves",
  "Feuilles d'épinette": "spruce_leaves",
  "Levier": "lever",
  "Pierre lumineuse": "glowstone",
  "Cadre luisant": "glow_frame",
  "Lichen lumineux": "glow_lichen",
  "Paratonnerre": "lightning_rod",
  "Paratonnerre exposé": "exposed_lightning_rod",
  "Paratonnerre patiné": "weathered_lightning_rod",
  "Paratonnerre oxydé": "oxidized_lightning_rod",
  "Paratonnerre ciré": "waxed_lightning_rod",
  "Paratonnerre exposé ciré": "waxed_exposed_lightning_rod",
  "Paratonnerre patiné ciré": "waxed_weathered_lightning_rod",
  "Paratonnerre oxydé ciré": "waxed_oxidized_lightning_rod",
  "Citrouille d'Halloween": "lit_pumpkin",
  "Bûche d'acacia": "acacia_log",
  "Bûche de chêne noir": "dark_oak_log",
  "Bûche de bouleau": "birch_log",
  "Bûche d'acajou": "jungle_log",
  "Bûche de chêne": "oak_log",
  "Bûche d'épinette": "spruce_log",
  "Bloc de magma": "magma",
  "Melon d'eau": "melon_block",
  "Tige de melon d'eau": "melon_stem",
  "Générateur de monstres": "mob_spawner",
  "Briques de pierre infestées": "infested_stone_bricks",
  "Brique de pierre ciselée infestée": "infested_chiseled_stone_bricks",
  "Fragments de pierres infestés": "infested_cobblestone",
  "Brique en pierre craquelée infestée": "infested_cracked_stone_bricks",
  "Briques de pierre moussues infestée": "infested_mossy_stone_bricks",
  "Pierre infestée": "infested_stone",
  "Bloc musical": "noteblock",
  "Mycélium": "mycelium",
  "Briques du Nether": "nether_brick",
  "Briques rouges du Nether": "red_nether_brick",
  "Clôture de briques du Nether": "nether_brick_fence",
  "Minerai de quartz du Nether": "quartz_ore",
  "Verrues du Nether": "nether_wart",
  "Bloc de verrues du Nether": "nether_wart_block",
  "Bloc de verrues tordues": "warped_wart_block",
  "Torche de redstone": "redstone_torch",
  "Torche des âmes": "soul_torch",
  "Obsidienne": "obsidian",
  "Minerai de charbon": "coal_ore",
  "Minerai de diamant": "diamond_ore",
  "Minerai d'émeraude": "emerald_ore",
  "Minerai d'or": "gold_ore",
  "Minerai de fer": "iron_ore",
  "Minerai de cuivre": "copper_ore",
  "Minerai de lapis-lazuli": "lapis_ore",
  "Minerai de redstone": "redstone_ore",
  "Minerai de redstone allumé": "lit_redstone_ore",
  "Observateur": "observer",
  "Piston": "piston",
  "Piston collant": "sticky_piston",
  "Collision de bras de piston": "piston_arm_collision",
  "Collision de bras de Piston collant": "sticky_piston_arm_collision",
  "Comparateur non alimenté": "unpowered_comparator",
  "Comparateur alimenté": "powered_comparator",
  "Répéteur non alimenté": "unpowered_repeater",
  "Répéteur alimenté": "powered_repeater",
  "Portail": "portal",
  "Pommes de terre": "potatoes",
  "Plaque de pression de pierre": "stone_pressure_plate",
  "Plaque de pression en chêne": "wooden_pressure_plate",
  "Plaque de pression en acacia": "acacia_pressure_plate",
  "Plaque de pression en bouleau": "birch_pressure_plate",
  "Plaque de pression en chêne noir": "dark_oak_pressure_plate",
  "Plaque de pression en acajou": "jungle_pressure_plate",
  "Plaque de pression en épinette": "spruce_pressure_plate",
  "Briques de prismarine": "prismarine_bricks",
  "Prismarine sombre": "dark_prismarine",
  "Prismarine": "prismarine",
  "Citrouille": "pumpkin",
  "Tige de citrouille": "pumpkin_stem",
  "Bloc de quartz ciselé": "chiseled_quartz_block",
  "Bloc de quartz": "quartz_block",
  "Pilier de quartz": "quartz_pillar",
  "Bloc de quartz lisse": "smooth_quartz",
  "Rails": "rail",
  "Champignon rouge": "red_mushroom",
  "Champignon cramoisi": "crimson_fungus",
  "Champignon tordu": "warped_fungus",
  "Bloc de champignon rouge": "red_mushroom_block",
  "Grès rouge ciselé": "chiseled_red_sandstone",
  "Grès rouge": "red_sandstone",
  "Grès rouge lisse": "smooth_red_sandstone",
  "Grès rouge taillé": "cut_red_sandstone",
  "Poudre de redstone": "redstone_wire",
  "Lampe à redstone": "redstone_lamp",
  "Lampe à redstone allumée": "lit_redstone_lamp",
  "Cannes à sucre": "reeds",
  "Sable": "sand",
  "Sable rouge": "red_sand",
  "Grès ciselé": "chiseled_sandstone",
  "Grès": "sandstone",
  "Grès lisse": "smooth_sandstone",
  "Grès taillé": "cut_sandstone",
  "Pousse d'acacia": "acacia_sapling",
  "Pousse de chêne noir": "dark_oak_sapling",
  "Pousse de bouleau": "birch_sapling",
  "Pousse d'acajou": "jungle_sapling",
  "Pousse de chêne": "oak_sapling",
  "Pousse d'épinette": "spruce_sapling",
  "Lanterne de mer": "sea_lantern",
  "Panneau": "standing_sign",
  "Panneau mural": "wall_sign",
  "Pancarte suspendue cramoisie": "crimson_hanging_sign",
  "Pancarte en épinette": "spruce_standing_sign",
  "Pancarte murale en épinette": "spruce_wall_sign",
  "Pancarte en bouleau": "birch_standing_sign",
  "Panneau mural en bouleau": "birch_wall_sign",
  "Pancarte suspendue en bouleau": "birch_hanging_sign",
  "Pancarte en acajou": "jungle_standing_sign",
  "Pancarte murale en bois tropical": "jungle_wall_sign",
  "Pancarte suspendue en acajou": "jungle_hanging_sign",
  "Pancarte en acacia": "acacia_standing_sign",
  "Panneau mural en acacia": "acacia_wall_sign",
  "Pancarte suspendue en acacia": "acacia_hanging_sign",
  "Pancarte suspendue en épinette": "spruce_hanging_sign",
  "Pancarte suspendue en chêne": "oak_hanging_sign",
  "Pancarte en chêne noir": "darkoak_standing_sign",
  "Pancarte murale en chêne noir": "darkoak_wall_sign",
  "Pancarte suspendue en chêne noir": "dark_oak_hanging_sign",
  "Bloc de gélatine": "slime",
  "Bloc de neige": "snow",
  "Éponge": "sponge",
  "Éponge mouillée": "wet_sponge",
  "Clôture en épinette": "spruce_fence",
  "Porte de clôture en épinette": "spruce_fence_gate",
  "Escaliers de briques": "brick_stairs",
  "Escaliers de briques du Nether": "nether_brick_stairs",
  "Escaliers de quartz": "quartz_stairs",
  "Escaliers de quartz lisse": "smooth_quartz_stairs",
  "Escaliers de grès rouge": "red_sandstone_stairs",
  "Escaliers de grès": "sandstone_stairs",
  "Escaliers en fragments de pierres": "stone_stairs",
  "Escaliers de pierre": "normal_stone_stairs",
  "Escaliers de briques de pierre": "stone_brick_stairs",
  "Escaliers en chêne": "oak_stairs",
  "Escaliers en acacia": "acacia_stairs",
  "Escaliers en bouleau": "birch_stairs",
  "Escaliers en chêne noir": "dark_oak_stairs",
  "Escaliers en acajou": "jungle_stairs",
  "Escaliers en épinette": "spruce_stairs",
  "Escaliers de purpur": "purpur_stairs",
  "Escaliers de prismarine": "prismarine_stairs",
  "Escaliers de prismarine sombre": "dark_prismarine_stairs",
  "Escaliers de briques de prismarine": "prismarine_bricks_stairs",
  "Escaliers de granite": "granite_stairs",
  "Escaliers de diorite": "diorite_stairs",
  "Escaliers d'andésite": "andesite_stairs",
  "Escaliers de granite poli": "polished_granite_stairs",
  "Escaliers de diorite polie": "polished_diorite_stairs",
  "Escaliers d'andésite polie": "polished_andesite_stairs",
  "Escaliers de briques de pierre moussues": "mossy_stone_brick_stairs",
  "Escaliers de grès rouge lisse": "smooth_red_sandstone_stairs",
  "Escaliers de grès lisse": "smooth_sandstone_stairs",
  "Escaliers en briques de pierre de l'Ender": "end_brick_stairs",
  "Escaliers en fragments de pierres moussus": "mossy_cobblestone_stairs",
  "Escaliers de briques rouges du Nether": "red_nether_brick_stairs",
  "Pierre lisse": "smooth_stone",
  "Bannière": "standing_banner",
  "Bannière murale": "wall_banner",
  "Andésite": "andesite",
  "Andésite polie": "polished_andesite",
  "Diorite": "diorite",
  "Diorite polie": "polished_diorite",
  "Granite": "granite",
  "Granite poli": "polished_granite",
  "Pierre": "stone",
  "Fragments de pierres": "cobblestone",
  "Briques de pierre ciselées": "chiseled_stone_bricks",
  "Briques en pierre craquelée": "cracked_stone_bricks",
  "Briques de pierre": "stone_bricks",
  "Briques de pierre moussues": "mossy_stone_bricks",
  "Tailleur de pierre": "stonecutter_block",
  "Fragments de pierres moussus": "mossy_cobblestone",
  "Dalle de briques": "brick_slab",
  "Dalle de fragments de pierres": "cobblestone_slab",
  "Dalle de pierre": "normal_stone_slab",
  "Dalle de briques du Nether": "nether_brick_slab",
  "Dalle de quartz": "quartz_slab",
  "Dalle de grès": "sandstone_slab",
  "Dalle de briques de pierre": "stone_brick_slab",
  "Dalle de bois": "petrified_oak_slab",
  "Dalle de pierre lisse": "smooth_stone_slab",
  "Dalle de grès rouge": "red_sandstone_double_slab",
  "Dalle de purpur": "purpur_slab",
  "Dalle double en purpur": "purpur_double_slab",
  "Dalle de prismarine": "prismarine_slab",
  "Dalle double en prismarine": "prismarine_double_slab",
  "Dalle de prismarine sombre": "dark_prismarine_slab",
  "Dalle double en prismarine sombre": "dark_prismarine_double_slab",
  "Dalle de briques de prismarine": "prismarine_brick_slab",
  "Dalle double en brique de prismarine": "prismarine_brick_double_slab",
  "Dalle en fragments de pierres moussus": "mossy_cobblestone_slab",
  "Dalle double de fragments de pierre moussus": "mossy_cobblestone_double_slab",
  "Dalle de briques rouges du Nether": "red_nether_brick_slab",
  "Dalle double de briques rouges du Nether": "red_nether_brick_double_slab",
  "Dalle de grès lisse": "smooth_sandstone_slab",
  "Dalle double de grès lisse": "smooth_sandstone_double_slab",
  "Dalle en briques de pierre de l'Ender": "end_stone_brick_slab",
  "Dalle double en briques de pierre de l'Ender": "end_stone_brick_double_slab",
  "Dalle de grès rouge lisse": "smooth_red_sandstone_slab",
  "Dalle double de grès rouge lisse": "smooth_red_sandstone_double_slab",
  "Dalle d'andésite polie": "polished_andesite_slab",
  "Dalle double d'andésite polie": "polished_andesite_double_slab",
  "Dalle d'andésite": "andesite_slab",
  "Dalle double d'andésite": "andesite_double_slab",
  "Dalle de diorite": "diorite_slab",
  "Dalle double de diorite": "diorite_double_slab",
  "Dalle de diorite polie": "polished_diorite_slab",
  "Dalle double de diorite polie": "polished_diorite_double_slab",
  "Dalle de granite": "granite_slab",
  "Dalle double de granite": "granite_double_slab",
  "Dalle de granite poli": "polished_granite_slab",
  "Dalle double de granite poli": "polished_granite_double_slab",
  "Dalle de briques de pierre moussues": "mossy_stone_brick_slab",
  "Dalle double de briques de pierre moussues": "mossy_stone_brick_double_slab",
  "Dalle de quartz lisse": "smooth_quartz_slab",
  "Dalle double de quartz lisse": "smooth_quartz_double_slab",
  "Dalle double de pierre": "normal_stone_double_slab",
  "Dalle de grès taillé": "cut_sandstone_slab",
  "Dalle double de grès taillé": "cut_sandstone_double_slab",
  "Dalle de grès rouge taillé": "cut_red_sandstone_slab",
  "Dalle double de grès rouge taillé": "cut_red_sandstone_double_slab",
  "Bloc de corail tube": "tube_coral_block",
  "Bloc de corail cerveau": "brain_coral_block",
  "Bloc de corail-bulle": "bubble_coral_block",
  "Bloc de corail de feu": "fire_coral_block",
  "Bloc de corail corné": "horn_coral_block",
  "Bloc de corail tube mort": "dead_tube_coral_block",
  "Bloc de corail cerveau mort": "dead_brain_coral_block",
  "Bloc de corail-bulle mort": "dead_bubble_coral_block",
  "Bloc de corail de feu mort": "dead_fire_coral_block",
  "Bloc de corail corné mort": "dead_horn_coral_block",
  "Fougère": "fern",
  "Herbe courte": "short_grass",
  "Dalle de briques de tuf": "tuff_brick_slab",
  "Dalle double en briques de tuf": "tuff_brick_double_slab",
  "Escaliers de briques de tuf": "tuff_brick_stairs",
  "Mur en briques de tuf": "tuff_brick_wall",
  "Briques de tuf": "tuff_bricks",
  "Dalle de tuf": "tuff_slab",
  "Dalle double de tuf": "tuff_double_slab",
  "Escaliers de tuf": "tuff_stairs",
  "Mur en tuf": "tuff_wall",
  "Herbe marine": "seagrass",
  "Cornichon de mer": "sea_pickle",
  "Œuf de tortue": "turtle_egg",
  "Colonne de bulles": "bubble_column",
  "Corail tube": "tube_coral",
  "Corail cerveau": "brain_coral",
  "Corail-bulle": "bubble_coral",
  "Corail de feu": "fire_coral",
  "Corail corné": "horn_coral",
  "Corail tube mort": "dead_tube_coral",
  "Corail cerveau mort": "dead_brain_coral",
  "Corail-bulle mort": "dead_bubble_coral",
  "Corail de feu mort": "dead_fire_coral",
  "Corail corné mort": "dead_horn_coral",
  "Gorgone de corail tube": "tube_coral_fan",
  "Gorgone de corail cerveau": "brain_coral_fan",
  "Gorgone de corail-bulle": "bubble_coral_fan",
  "Gorgone de corail de feu": "fire_coral_fan",
  "Gorgone de corail corné": "horn_coral_fan",
  "Gorgone de corail tube mort": "dead_tube_coral_fan",
  "Gorgone de corail cerveau morte": "dead_brain_coral_fan",
  "Gorgone de corail-bulle mort": "dead_bubble_coral_fan",
  "Gorgone de corail de feu morte": "dead_fire_coral_fan",
  "Gorgone de corail corné mort": "dead_horn_coral_fan",
  "Gorgone murale de corail-bulle mort": "dead_bubble_coral_wall_fan",
  "Gorgone murale de corail corné mort": "dead_horn_coral_wall_fan",
  "Colonie murale de corail de feu mort": "dead_fire_coral_wall_fan",
  "Gorgone murale de corail tube": "tube_coral_wall_fan",
  "Colonie murale de corail cerveau mort": "dead_brain_coral_wall_fan",
  "Colonie murale de corail cerveau": "brain_coral_wall_fan",
  "Gorgone murale de corail corné": "horn_coral_wall_fan",
  "Colonie murale de corail de feu": "fire_coral_wall_fan",
  "Gorgone murale de corail-bulle": "bubble_coral_wall_fan",
  "Colonie murale de corail tube mort": "dead_tube_coral_wall_fan",
  "Vitre": "glass_pane",
  "TNT": "tnt",
  "Neige": "snow_layer",
  "Torche": "torch",
  "Trappe en chêne": "trapdoor",
  "Trappe en acacia": "acacia_trapdoor",
  "Trappe en bouleau": "birch_trapdoor",
  "Trappe en chêne noir": "dark_oak_trapdoor",
  "Trappe en acajou": "jungle_trapdoor",
  "Trappe en épinette": "spruce_trapdoor",
  "Fil de déclenchement": "trip_wire",
  "Crochet": "tripwire_hook",
  "Lianes": "vine",
  "Lianes pleureuses": "weeping_vines",
  "Lianes torsadées": "twisting_vines",
  "Eau": "water",
  "Nénuphar": "waterlily",
  "Toile d'araignée": "web",
  "Plaque de lourde pesée": "heavy_weighted_pressure_plate",
  "Plaque de légère pesée": "light_weighted_pressure_plate",
  "Pierre de l'Ender": "end_stone",
  "Briques de pierre de l'Ender": "end_bricks",
  "Planches d'acacia": "acacia_planks",
  "Planches de chêne noir": "dark_oak_planks",
  "Planches de bouleau": "birch_planks",
  "Planches d'acajou": "jungle_planks",
  "Planches de chêne": "oak_planks",
  "Planches d'épinette": "spruce_planks",
  "Dalle en acacia": "acacia_slab",
  "Dalle double d'acacia": "acacia_double_slab",
  "Dalle en chêne noir": "dark_oak_slab",
  "Dalle double en chêne noir": "dark_oak_double_slab",
  "Dalle en bouleau": "birch_slab",
  "Dalle double de bouleau": "birch_double_slab",
  "Dalle en acajou": "jungle_slab",
  "Dalle double de bois tropical": "jungle_double_slab",
  "Dalle en chêne": "oak_slab",
  "Dalle double en chêne": "oak_double_slab",
  "Dalle en épinette": "spruce_slab",
  "Dalle double en épinette": "spruce_double_slab",
  "Tapis noir": "black_carpet",
  "Tapis bleu": "blue_carpet",
  "Tapis brun": "brown_carpet",
  "Tapis cyan": "cyan_carpet",
  "Tapis gris": "gray_carpet",
  "Tapis vert": "green_carpet",
  "Tapis bleu pâle": "light_blue_carpet",
  "Tapis vert lime": "lime_carpet",
  "Tapis magenta": "magenta_carpet",
  "Tapis orange": "orange_carpet",
  "Tapis rose": "pink_carpet",
  "Tapis mauve": "purple_carpet",
  "Tapis rouge": "red_carpet",
  "Tapis gris pâle": "light_gray_carpet",
  "Tapis blanc": "white_carpet",
  "Tapis jaune": "yellow_carpet",
  "Fabricateur": "crafter",
  "Établi": "crafting_table",
  "Bouton en chêne pâle": "pale_oak_button",
  "Double dalle en chêne pâle": "pale_oak_double_slab",
  "Clôture en chêne pâle": "pale_oak_fence",
  "Porte de clôture en chêne pâle": "pale_oak_fence_gate",
  "Bûche de chêne pâle": "pale_oak_log",
  "Planches de chêne pâle": "pale_oak_planks",
  "Plaque de pression en chêne pâle": "pale_oak_pressure_plate",
  "Panneau en chêne pâle": "pale_oak_standing_sign",
  "Panneau mural en chêne pâle": "pale_oak_wall_sign",
  "Pancarte suspendue en chêne pâle": "pale_oak_hanging_sign",
  "Dalle en chêne pâle": "pale_oak_slab",
  "Escalier en chêne pâle": "pale_oak_stairs",
  "Trappe en chêne pâle": "pale_oak_trapdoor",
  "Bois de chêne pâle": "pale_oak_wood",
  "Bûche de chêne blanc écorcée": "stripped_pale_oak_log",
  "Bois de chêne blanc écorcé": "stripped_pale_oak_wood",
  "Mousse pâle suspendue": "pale_hanging_moss",
  "Bloc de mousse pâle": "pale_moss_block",
  "Tapis de mousse pâle": "pale_moss_carpet",
  "Cœur de grinceur": "creaking_heart",
  "Œil de nuit ouvert": "open_eyeblossom",
  "Œil de nuit fermé": "closed_eyeblossom",
  "Briques de résine": "resin_bricks",
  "Dalle double de briques de résine": "resin_brick_double_slab",
  "Dalle de briques de résine": "resin_brick_slab",
  "Escaliers de briques de résine": "resin_brick_stairs",
  "Mur en briques de résine": "resin_brick_wall",
  "Briques de résine ciselées": "chiseled_resin_bricks",
  "Bloc de résine": "resin_block",
  "Amas de résine": "resin_clump",
  "Terre cuite blanche émaillée": "white_glazed_terracotta",
  "Terre cuite orange émaillée": "orange_glazed_terracotta",
  "Terre cuite magenta émaillée": "magenta_glazed_terracotta",
  "Terre cuite bleu pâle émaillée": "light_blue_glazed_terracotta",
  "Terre cuite jaune émaillée": "yellow_glazed_terracotta",
  "Terre cuite vert lime émaillée": "lime_glazed_terracotta",
  "Terre cuite rose émaillée": "pink_glazed_terracotta",
  "Terre cuite grise émaillée": "gray_glazed_terracotta",
  "Terre cuite gris pâle émaillée": "silver_glazed_terracotta",
  "Terre cuite cyan émaillée": "cyan_glazed_terracotta",
  "Terre cuite mauve émaillée": "purple_glazed_terracotta",
  "Terre cuite bleue émaillée": "blue_glazed_terracotta",
  "Terre cuite brune émaillée": "brown_glazed_terracotta",
  "Terre cuite verte émaillée": "green_glazed_terracotta",
  "Terre cuite rouge émaillée": "red_glazed_terracotta",
  "Terre cuite noire émaillée": "black_glazed_terracotta",
  "Béton noir": "black_concrete",
  "Béton rouge": "red_concrete",
  "Béton vert": "green_concrete",
  "Béton brun": "brown_concrete",
  "Béton bleu": "blue_concrete",
  "Béton mauve": "purple_concrete",
  "Béton cyan": "cyan_concrete",
  "Béton gris pâle": "light_gray_concrete",
  "Béton gris": "gray_concrete",
  "Béton rose": "pink_concrete",
  "Béton vert lime": "lime_concrete",
  "Béton jaune": "yellow_concrete",
  "Béton bleu pâle": "light_blue_concrete",
  "Béton magenta": "magenta_concrete",
  "Béton orange": "orange_concrete",
  "Béton blanc": "white_concrete",
  "Béton noir en poudre": "black_concrete_powder",
  "Béton rouge en poudre": "red_concrete_powder",
  "Béton vert en poudre": "green_concrete_powder",
  "Béton brun en poudre": "brown_concrete_powder",
  "Béton bleu en poudre": "blue_concrete_powder",
  "Béton mauve en poudre": "purple_concrete_powder",
  "Béton cyan en poudre": "cyan_concrete_powder",
  "Béton gris pâle en poudre": "light_gray_concrete_powder",
  "Béton gris en poudre": "gray_concrete_powder",
  "Béton rose en poudre": "pink_concrete_powder",
  "Béton vert lime en poudre": "lime_concrete_powder",
  "Béton jaune en poudre": "yellow_concrete_powder",
  "Béton bleu pâle en poudre": "light_blue_concrete_powder",
  "Béton magenta en poudre": "magenta_concrete_powder",
  "Béton orange en poudre": "orange_concrete_powder",
  "Béton blanc en poudre": "white_concrete_powder",
  "Bûche d'épinette écorcée": "stripped_spruce_log",
  "Bûche de chêne noir écorcée": "stripped_dark_oak_log",
  "Bûche de bouleau écorcée": "stripped_birch_log",
  "Bûche d'acajou écorcée": "stripped_jungle_log",
  "Bûche de chêne écorcée": "stripped_oak_log",
  "Bûche d'acacia écorcée": "stripped_acacia_log",
  "Bambou": "bamboo",
  "Échafaudage": "scaffolding",
  "Meule": "grindstone",
  "Table de cartographie": "cartography_table",
  "Lanterne": "lantern",
  "Lanterne des âmes": "soul_lantern",
  "Fumoir": "smoker",
  "Fumoir allumé": "lit_smoker",
  "Table de forge": "smithing_table",
  "Tonneau": "barrel",
  "Feu de camp": "campfire",
  "Métier à tisser": "loom",
  "Lutrin": "lectern",
  "Buisson de baies sucrées": "sweet_berry_bush",
  "Bois de chêne": "oak_wood",
  "Bois d'épinette": "spruce_wood",
  "Bois de bouleau": "birch_wood",
  "Bois d'acajou": "jungle_wood",
  "Bois d'acacia": "acacia_wood",
  "Bois de chêne noir": "dark_oak_wood",
  "Bois de chêne écorcé": "stripped_oak_wood",
  "Bois d'épinette écorcé": "stripped_spruce_wood",
  "Bois de bouleau écorcé": "stripped_birch_wood",
  "Bois d'acajou écorcé": "stripped_jungle_wood",
  "Bois d'acacia écorcé": "stripped_acacia_wood",
  "Bois de chêne noir écorcé": "stripped_dark_oak_wood",
  "Bloc de netherite": "netherite_block",
  "Débris antiques": "ancient_debris",
  "Minerai d'or du Nether": "nether_gold_ore",
  "Ancre de réapparition": "respawn_anchor",
  "Obsidienne pleureuse": "crying_obsidian",
  "Neige poudreuse": "powder_snow",
  "Profondoise": "deepslate",
  "Profondoise infestée": "infested_deepslate",
  "Profondoise concassée": "cobbled_deepslate",
  "Bloc de spéléothème": "dripstone_block",
  "Spéléothème pointu": "pointed_dripstone",
  "Dalle de profondoise concassée": "cobbled_deepslate_slab",
  "Escaliers de profondoise concassée": "cobbled_deepslate_stairs",
  "Mur de profondoise concassée": "cobbled_deepslate_wall",
  "Profondoise polie": "polished_deepslate",
  "Dalle de profondoise polie": "polished_deepslate_slab",
  "Escaliers de profondoise polie": "polished_deepslate_stairs",
  "Mur de profondoise polie": "polished_deepslate_wall",
  "Tuiles de profondoise": "deepslate_tiles",
  "Dalle de tuiles de profondoise": "deepslate_tile_slab",
  "Escaliers de tuiles de profondoise": "deepslate_tile_stairs",
  "Mur de tuiles de profondoise": "deepslate_tile_wall",
  "Briques de profondoise": "deepslate_bricks",
  "Dalle de briques de profondoise": "deepslate_brick_slab",
  "Escaliers de briques de profondoise": "deepslate_brick_stairs",
  "Mur de briques de profondoise": "deepslate_brick_wall",
  "Profondoise ciselée": "chiseled_deepslate",
  "Dalle double de profondoise concassée": "cobbled_deepslate_double_slab",
  "Dalle double de profondoise polie": "polished_deepslate_double_slab",
  "Dalle double de tuiles de profondoise": "deepslate_tile_double_slab",
  "Dalle double de briques de profondoise": "deepslate_brick_double_slab",
  "Minerai de lapis-lazuli de profondoise": "deepslate_lapis_ore",
  "Minerai de fer de profondoise": "deepslate_iron_ore",
  "Minerai d'or de profondoise": "deepslate_gold_ore",
  "Minerai de redstone de profondoise": "deepslate_redstone_ore",
  "Minerai de redstone de profondoise texturé": "lit_deepslate_redstone_ore",
  "Minerai de diamant de profondoise": "deepslate_diamond_ore",
  "Minerai de charbon de profondoise": "deepslate_coal_ore",
  "Minerai d'émeraude de profondoise": "deepslate_emerald_ore",
  "Minerai de cuivre de profondoise": "deepslate_copper_ore",
  "Tuiles de profondoise craquelées": "cracked_deepslate_tiles",
  "Briques de profondoise craquelées": "cracked_deepslate_bricks",
  "Sarracénie": "pitcher_plant",
  "Culture de sarracénie": "pitcher_crop",
  "Œuf de Renifleur": "sniffer_egg",
  "Torche-fleur": "torchflower",
  "Bloc de cuivre": "copper_block",
  "Bloc de cuivre exposé": "exposed_copper",
  "Bloc de cuivre patiné": "weathered_copper",
  "Bloc de cuivre oxydé": "oxidized_copper",
  "Bloc de cuivre ciré": "waxed_copper",
  "Bloc de cuivre exposé ciré": "waxed_exposed_copper",
  "Bloc de cuivre patiné ciré": "waxed_weathered_copper",
  "Bloc de cuivre oxydé ciré": "waxed_oxidized_copper",
  "Cuivre taillé": "cut_copper",
  "Cuivre taillé exposé": "exposed_cut_copper",
  "Cuivre taillé patiné": "weathered_cut_copper",
  "Cuivre taillé oxydé": "oxidized_cut_copper",
  "Cuivre taillé ciré": "waxed_cut_copper",
  "Cuivre taillé exposé ciré": "waxed_exposed_cut_copper",
  "Cuivre taillé patiné ciré": "waxed_weathered_cut_copper",
  "Cuivre taillé oxydé ciré": "waxed_oxidized_cut_copper",
  "Escaliers de cuivre taillé": "cut_copper_stairs",
  "Escaliers de cuivre taillé exposé": "exposed_cut_copper_stairs",
  "Escaliers de cuivre taillé patiné": "weathered_cut_copper_stairs",
  "Escaliers de cuivre taillé oxydé": "oxidized_cut_copper_stairs",
  "Escaliers de cuivre taillé ciré": "waxed_cut_copper_stairs",
  "Escaliers de cuivre taillé exposé ciré": "waxed_exposed_cut_copper_stairs",
  "Escaliers de cuivre taillé patiné ciré": "waxed_weathered_cut_copper_stairs",
  "Escaliers de cuivre taillé oxydé ciré": "waxed_oxidized_cut_copper_stairs",
  "Dalle de cuivre taillé": "cut_copper_slab",
  "Dalle double de cuivre taillé": "double_cut_copper_slab",
  "Dalle de cuivre taillé exposé": "exposed_cut_copper_slab",
  "Dalle double de cuivre taillé exposé": "exposed_double_cut_copper_slab",
  "Dalle de cuivre taillé patiné": "weathered_cut_copper_slab",
  "Dalle double de cuivre taillé patiné": "weathered_double_cut_copper_slab",
  "Dalle de cuivre taillé oxydé": "oxidized_cut_copper_slab",
  "Dalle double de cuivre taillé oxydé": "oxidized_double_cut_copper_slab",
  "Dalle de cuivre taillé ciré": "waxed_cut_copper_slab",
  "Dalle double de cuivre taillé ciré": "waxed_double_cut_copper_slab",
  "Dalle de cuivre taillé exposé ciré": "waxed_exposed_cut_copper_slab",
  "Dalle double de cuivre taillé exposé ciré": "waxed_exposed_double_cut_copper_slab",
  "Dalle de cuivre taillé patiné ciré": "waxed_weathered_cut_copper_slab",
  "Dalle double de cuivre taillé patiné ciré": "waxed_weathered_double_cut_copper_slab",
  "Dalle de cuivre taillé oxydé ciré": "waxed_oxidized_cut_copper_slab",
  "Dalle double de cuivre taillé oxydé ciré": "waxed_oxidized_double_cut_copper_slab",
  "Cuivre ciselé": "chiseled_copper",
  "Cuivre ciselé exposé": "exposed_chiseled_copper",
  "Cuivre ciselé oxydé": "oxidized_chiseled_copper",
  "Cuivre ciselé ciré": "waxed_chiseled_copper",
  "Cuivre ciselé exposé ciré": "waxed_exposed_chiseled_copper",
  "Cuivre ciselé oxydé ciré": "waxed_oxidized_chiseled_copper",
  "Cuivre ciselé patiné ciré": "waxed_weathered_chiseled_copper",
  "Cuivre ciselé patiné": "weathered_chiseled_copper",
  "Lampe en cuivre": "copper_bulb",
  "Lampe en cuivre exposé": "exposed_copper_bulb",
  "Lampe en cuivre oxydé": "oxidized_copper_bulb",
  "Lampe en cuivre ciré": "waxed_copper_bulb",
  "Lampe en cuivre exposé ciré": "waxed_exposed_copper_bulb",
  "Ampoule en cuivre oxydé ciré": "waxed_oxidized_copper_bulb",
  "Lampe en cuivre patiné ciré": "waxed_weathered_copper_bulb",
  "Lampe en cuivre patiné": "weathered_copper_bulb",
  "Porte en cuivre": "copper_door",
  "Porte en cuivre exposé": "exposed_copper_door",
  "Porte en cuivre oxydé": "oxidized_copper_door",
  "Porte en cuivre ciré": "waxed_copper_door",
  "Porte en cuivre exposé ciré": "waxed_exposed_copper_door",
  "Porte en cuivre oxydé ciré": "waxed_oxidized_copper_door",
  "Porte en cuivre patiné ciré": "waxed_weathered_copper_door",
  "Porte en cuivre patiné": "weathered_copper_door",
  "Grille en cuivre": "copper_grate",
  "Grille en cuivre exposé": "exposed_copper_grate",
  "Grille en cuivre oxydé": "oxidized_copper_grate",
  "Grille en cuivre ciré": "waxed_copper_grate",
  "Grille en cuivre exposé ciré": "waxed_exposed_copper_grate",
  "Grille en cuivre oxydé ciré": "waxed_oxidized_copper_grate",
  "Grille en cuivre patiné ciré": "waxed_weathered_copper_grate",
  "Grille en cuivre patiné": "weathered_copper_grate",
  "Trappe en cuivre": "copper_trapdoor",
  "Trappe en cuivre exposé": "exposed_copper_trapdoor",
  "Trappe en cuivre oxydé": "oxidized_copper_trapdoor",
  "Trappe en cuivre ciré": "waxed_copper_trapdoor",
  "Trappe en cuivre exposé ciré": "waxed_exposed_copper_trapdoor",
  "Trappe en cuivre oxydé ciré": "waxed_oxidized_copper_trapdoor",
  "Trappe en cuivre patiné ciré": "waxed_weathered_copper_trapdoor",
  "Trappe en cuivre patiné": "weathered_copper_trapdoor",
  "Bloc de cuivre brut": "raw_copper_block",
  "Bloc de fer brut": "raw_iron_block",
  "Bloc d'or brut": "raw_gold_block",
  "Bougie": "candle",
  "Bougie blanche": "white_candle",
  "Bougie orange": "orange_candle",
  "Bougie magenta": "magenta_candle",
  "Bougie bleu pâle": "light_blue_candle",
  "Bougie jaune": "yellow_candle",
  "Bougie vert lime": "lime_candle",
  "Bougie rose": "pink_candle",
  "Bougie grise": "gray_candle",
  "Bougie gris pâle": "light_gray_candle",
  "Bougie cyan": "cyan_candle",
  "Bougie mauve": "purple_candle",
  "Bougie bleue": "blue_candle",
  "Bougie brune": "brown_candle",
  "Bougie verte": "green_candle",
  "Bougie rouge": "red_candle",
  "Bougie noire": "black_candle",
  "Gâteau avec bougie": "candle_cake",
  "Gâteau avec bougie blanche": "white_candle_cake",
  "Gâteau avec bougie orange": "orange_candle_cake",
  "Gâteau avec bougie magenta": "magenta_candle_cake",
  "Gâteau avec bougie bleu pâle": "light_blue_candle_cake",
  "Gâteau avec bougie jaune": "yellow_candle_cake",
  "Gâteau avec bougie vert lime": "lime_candle_cake",
  "Gâteau avec bougie rose": "pink_candle_cake",
  "Gâteau avec bougie grise": "gray_candle_cake",
  "Gâteau avec bougie gris pâle": "light_gray_candle_cake",
  "Gâteau avec bougie cyan": "cyan_candle_cake",
  "Gâteau avec bougie mauve": "purple_candle_cake",
  "Gâteau avec bougie bleue": "blue_candle_cake",
  "Gâteau avec bougie brune": "brown_candle_cake",
  "Gâteau avec bougie verte": "green_candle_cake",
  "Gâteau avec bougie rouge": "red_candle_cake",
  "Gâteau avec bougie noire": "black_candle_cake",
  "Bloc d'améthyste": "amethyst_block",
  "Druse d'améthyste": "budding_amethyst",
  "Agglomérat d'améthyste": "amethyst_cluster",
  "Grand cristal d'améthyste": "large_amethyst_bud",
  "Cristal d'améthyste moyen": "medium_amethyst_bud",
  "Petit cristal d'améthyste": "small_amethyst_bud",
  "Tuf": "tuff",
  "Calcite": "calcite",
  "Verre teinté": "tinted_glass",
  "Basalte lisse": "smooth_basalt",
  "Fleurs sauvages": "wildflowers",
  "Buisson de mouches à feu": "firefly_bush",
  "Buisson": "bush",
  "Feuilles mortes": "leaf_litter",
  "Fleur de cactus": "cactus_flower",
  "Herbe sèche courte": "short_dry_grass",
  "Hautes herbes sèches": "tall_dry_grass",
  "Ghast desséché": "dried_ghast",
  "Coffre en cuivre": "copper_chest",
  "Coffre en cuivre exposé": "exposed_copper_chest",
  "Coffre en cuivre patiné": "weathered_copper_chest",
  "Coffre en cuivre oxydé": "oxidized_copper_chest",
  "Coffre en cuivre ciré": "waxed_copper_chest",
  "Coffre en cuivre exposé ciré": "waxed_exposed_copper_chest",
  "Coffre en cuivre patiné ciré": "waxed_weathered_copper_chest",
  "Coffre en cuivre oxydé ciré": "waxed_oxidized_copper_chest",
  "Étagère en acacia": "acacia_shelf",
  "Étagère en bambou": "bamboo_shelf",
  "Étagère en bouleau": "birch_shelf",
  "Étagère en cerisier": "cherry_shelf",
  "Étagère cramoisie": "crimson_shelf",
  "Étagère en chêne noir": "dark_oak_shelf",
  "Étagère en bois tropical": "jungle_shelf",
  "Étagère en palétuvier": "mangrove_shelf",
  "Étagère en chêne": "oak_shelf",
  "Étagère en chêne pâle": "pale_oak_shelf",
  "Étagère en épinette": "spruce_shelf",
  "Étagère tordue": "warped_shelf",
  "Statue de golem de cuivre": "copper_golem_statue",
  "Statue de golem de cuivre exposé": "exposed_copper_golem_statue",
  "Statue de golem de cuivre patiné": "weathered_copper_golem_statue",
  "Statue de golem de cuivre oxydé": "oxidized_copper_golem_statue",
  "Statue de golem de cuivre ciré": "waxed_copper_golem_statue",
  "Statue de golem de cuivre exposé ciré": "waxed_exposed_copper_golem_statue",
  "Statue de golem de cuivre patiné ciré": "waxed_weathered_copper_golem_statue",
  "Statue de golem de cuivre oxydé ciré": "waxed_oxidized_copper_golem_statue",
  "Chaîne en cuivre": "copper_chain",
  "Chaîne en cuivre exposé": "exposed_copper_chain",
  "Chaîne en cuivre patiné": "weathered_copper_chain",
  "Chaîne en cuivre oxydé": "oxidized_copper_chain",
  "Chaîne en cuivre ciré": "waxed_copper_chain",
  "Chaîne en cuivre exposé ciré": "waxed_exposed_copper_chain",
  "Chaîne en cuivre patiné ciré": "waxed_weathered_copper_chain",
  "Chaîne en cuivre oxydé ciré": "waxed_oxidized_copper_chain",
  "Barreaux de cuivre": "copper_bars",
  "Barreaux de cuivre exposé": "exposed_copper_bars",
  "Barreaux de cuivre patiné": "weathered_copper_bars",
  "Barreaux de cuivre oxydé": "oxidized_copper_bars",
  "Barreaux de cuivre ciré": "waxed_copper_bars",
  "Barreaux de cuivre exposé ciré": "waxed_exposed_copper_bars",
  "Barreaux de cuivre patiné ciré": "waxed_weathered_copper_bars",
  "Barreaux de cuivre oxydé ciré": "waxed_oxidized_copper_bars",
  "Lanterne en cuivre": "copper_lantern",
  "Lanterne en cuivre exposé": "exposed_copper_lantern",
  "Lanterne en cuivre patiné": "weathered_copper_lantern",
  "Lanterne en cuivre oxydé": "oxidized_copper_lantern",
  "Lanterne en cuivre ciré": "waxed_copper_lantern",
  "Lanterne en cuivre exposé ciré": "waxed_exposed_copper_lantern",
  "Lanterne en cuivre patiné ciré": "waxed_weathered_copper_lantern",
  "Lanterne en cuivre oxydé ciré": "waxed_oxidized_copper_lantern",
  "Torche de cuivre": "copper_torch",
  "Chaîne en fer": "iron_chain",
  "Pissenlit doré": "golden_dandelion",
  "Soufre": "sulfur",
  "Dalle en soufre": "sulfur_slab",
  "Dalle double en soufre": "sulfur_double_slab",
  "Escalier en soufre": "sulfur_stairs",
  "Muret en soufre": "sulfur_wall",
  "Soufre poli": "polished_sulfur",
  "Dalle en soufre poli": "polished_sulfur_slab",
  "Dalle double en soufre poli": "polished_sulfur_double_slab",
  "Escalier en soufre poli": "polished_sulfur_stairs",
  "Muret en soufre poli": "polished_sulfur_wall",
  "Briques de soufre": "sulfur_bricks",
  "Dalle de briques de soufre": "sulfur_brick_slab",
  "Dalle double de briques de soufre": "sulfur_brick_double_slab",
  "Escalier en briques de soufre": "sulfur_brick_stairs",
  "Muret de briques de soufre": "sulfur_brick_wall",
  "Soufre ciselé": "chiseled_sulfur",
  "Soufre concentré": "potent_sulfur",
  "Cinabre": "cinnabar",
  "Dalle en cinabre": "cinnabar_slab",
  "Dalle double en cinabre": "cinnabar_double_slab",
  "Escalier en cinabre": "cinnabar_stairs",
  "Muret en cinabre": "cinnabar_wall",
  "Cinabre poli": "polished_cinnabar",
  "Dalle en cinabre poli": "polished_cinnabar_slab",
  "Dalle double en cinabre poli": "polished_cinnabar_double_slab",
  "Escalier en cinabre poli": "polished_cinnabar_stairs",
  "Muret en cinabre poli": "polished_cinnabar_wall",
  "Briques de cinabre": "cinnabar_bricks",
  "Dalle de briques de cinabre": "cinnabar_brick_slab",
  "Dalle double de briques de cinabre": "cinnabar_brick_double_slab",
  "Escalier en briques de cinabre": "cinnabar_brick_stairs",
  "Muret de briques de cinabre": "cinnabar_brick_wall",
  "Cinabre ciselé": "chiseled_cinnabar",
  "Pique de soufre": "sulfur_spike"
}